posjoy/__init__.py
posjoy/posjoy.py
posjoy-0.0.4.dist-info/METADATA
posjoy-0.0.4.dist-info/WHEEL
posjoy-0.0.4.dist-info/top_level.txt
posjoy-0.0.4.dist-info/RECORD
